{
  "funds": [
    { "ticker": "AAPL", "name": "Apple Inc." },
    { "ticker": "ABBV", "name": "AbbVie Inc." },
    { "ticker": "AGTHX", "name": "American Funds The Growth Fund of America Class A" },
    { "ticker": "AMD", "name": "Advanced Micro Devices Inc." },
    { "ticker": "AMGN", "name": "Amgen Inc." },
    { "ticker": "AMZN", "name": "Amazon.com Inc." },
    { "ticker": "ASML", "name": "ASML Holding N.V." },
    { "ticker": "AVGO", "name": "Broadcom Inc." },
    { "ticker": "BAC", "name": "Bank of America Corporation" },
    { "ticker": "BA", "name": "The Boeing Company" },
    { "ticker": "BND", "name": "Vanguard Total Bond Market ETF" },
    { "ticker": "CAT", "name": "Caterpillar Inc." },
    { "ticker": "C", "name": "Citigroup Inc." },
    { "ticker": "COST", "name": "Costco Wholesale Corporation" },
    { "ticker": "CSCO", "name": "Cisco Systems Inc." },
    { "ticker": "CVX", "name": "Chevron Corporation" },
    { "ticker": "DIS", "name": "The Walt Disney Company" },
    { "ticker": "FXAIX", "name": "Fidelity 500 Index Fund" },
    { "ticker": "FZCXX", "name": "Fidelity Government Money Market Fund Premium Class" },
    { "ticker": "GFACX", "name": "American Funds The Growth Fund of America Class C" },
    { "ticker": "GOOG", "name": "Alphabet Inc. Class C" },
    { "ticker": "GOOGL", "name": "Alphabet Inc. Class A" },
    { "ticker": "GS", "name": "The Goldman Sachs Group Inc." },
    { "ticker": "HD", "name": "The Home Depot Inc." },
    { "ticker": "IBM", "name": "International Business Machines Corporation" },
    { "ticker": "INTC", "name": "Intel Corporation" },
    { "ticker": "JNJ", "name": "Johnson & Johnson" },
    { "ticker": "JPM", "name": "JPMorgan Chase & Co." },
    { "ticker": "KO", "name": "The Coca-Cola Company" },
    { "ticker": "LLY", "name": "Eli Lilly and Company" },
    { "ticker": "MA", "name": "Mastercard Incorporated" },
    { "ticker": "MCD", "name": "McDonald's Corporation" },
    { "ticker": "META", "name": "Meta Platforms Inc." },
    { "ticker": "MSFT", "name": "Microsoft Corporation" },
    { "ticker": "MS", "name": "Morgan Stanley" },
    { "ticker": "MU", "name": "Micron Technology Inc." },
    { "ticker": "NFLX", "name": "Netflix Inc." },
    { "ticker": "NVDA", "name": "NVIDIA Corporation" },
    { "ticker": "ORCL", "name": "Oracle Corporation" },
    { "ticker": "PEP", "name": "PepsiCo Inc." },
    { "ticker": "PG", "name": "The Procter & Gamble Company" },
    { "ticker": "QQQ", "name": "Invesco QQQ Trust" },
    { "ticker": "SCHF", "name": "Schwab International Equity ETF" },
    { "ticker": "SCHG", "name": "Schwab U.S. Large-Cap Growth ETF" },
    { "ticker": "SCHX", "name": "Schwab U.S. Large-Cap ETF" },
    { "ticker": "SHOP", "name": "Shopify Inc." },
    { "ticker": "SPY", "name": "State Street SPDR S&P 500 ETF Trust" },
    { "ticker": "SPYM", "name": "State Street SPDR Portfolio S&P 500 ETF" },
    { "ticker": "SPAXX", "name": "Fidelity Government Money Market Fund" },
    { "ticker": "TSM", "name": "Taiwan Semiconductor Manufacturing Company Limited" },
    { "ticker": "TSLA", "name": "Tesla Inc." },
    { "ticker": "UNH", "name": "UnitedHealth Group Incorporated" },
    { "ticker": "USHY", "name": "iShares Broad USD High Yield Corporate Bond ETF" },
    { "ticker": "V", "name": "Visa Inc." },
    { "ticker": "VBTLX", "name": "Vanguard Total Bond Market Index Fund Admiral Shares" },
    { "ticker": "VFIAX", "name": "Vanguard 500 Index Fund Admiral Shares" },
    { "ticker": "VINIX", "name": "Vanguard Institutional Index Fund" },
    { "ticker": "VNQ", "name": "Vanguard Real Estate ETF" },
    { "ticker": "VTSAX", "name": "Vanguard Total Stock Market Index Fund Admiral Shares" },
    { "ticker": "VTI", "name": "Vanguard Total Stock Market ETF" },
    { "ticker": "VTIAX", "name": "Vanguard Total International Stock Index Fund Admiral Shares" },
    { "ticker": "VOO", "name": "Vanguard S&P 500 ETF" },
    { "ticker": "VEA", "name": "Vanguard FTSE Developed Markets ETF" },
    { "ticker": "WMT", "name": "Walmart Inc." },
    { "ticker": "XLF", "name": "State Street Financial Select Sector SPDR ETF" },
    { "ticker": "XLE", "name": "State Street Energy Select Sector SPDR ETF" },
    { "ticker": "XLK", "name": "State Street Technology Select Sector SPDR ETF" },
    { "ticker": "XLU", "name": "State Street Utilities Select Sector SPDR ETF" },
    { "ticker": "XOM", "name": "Exxon Mobil Corporation" }
  ]
}